[
  {
    "id": 1,
    "name": "plkdesai2005",
    "email": "plkdesai2005@gmail.com",
    "subject": "General Query",
    "message": "niceeeeeeeee",
    "timestamp": "2026-01-20T20:06:59.908695",
    "recipient": "ridewisebike@gmail.com"
  },
  {
    "id": 2,
    "name": "plkdesai2005",
    "email": "plkdesai2005@gmail.com",
    "subject": "General Query",
    "message": "good experience",
    "timestamp": "2026-01-20T21:06:05.231575",
    "recipient": "ridewisebike@gmail.com"
  },
  {
    "id": 3,
    "name": "abc",
    "email": "abc@gmail.com",
    "subject": "General Query",
    "message": "niceeeeeeeee",
    "timestamp": "2026-01-20T22:22:45.351671",
    "recipient": "ridewisebike@gmail.com"
  }
]